flaskrestgen/__init__.py
flaskrestgen/envelop.py
flaskrestgen/errors.py
flaskrestgen/generator.py
flaskrestgen-0.4.dist-info/DESCRIPTION.rst
flaskrestgen-0.4.dist-info/METADATA
flaskrestgen-0.4.dist-info/RECORD
flaskrestgen-0.4.dist-info/WHEEL
flaskrestgen-0.4.dist-info/metadata.json
flaskrestgen-0.4.dist-info/top_level.txt
