Metadata-Version: 1.1
Name: flaskrestgen
Version: 0.4
Summary: A restful API generator for flask/sqlalchemy declarative models.
Home-page: https://github.com/RobusGauli/flask-restapi-gen
Author: Robus Gauli
Author-email: robusgauli@gmail.com
License: UNKNOWN
Download-URL: https://github.com/RobusGauli/flask-restapi-gen/archive/0.4.tar.gz
Keywords: flask,restapi,restful,restgenerator
Platform: UNKNOWN
